{
  "@context": "http://iiif.io/api/presentation/2/context.json",
  "@id": "https://alicia-ka.github.io/iiif-test/annotations/G30495-02/list_p49.json",
  "@type": "sc:AnnotationList",
  "label": "Annotations for page 49",
  "resources": [
    {
      "@id": "https://alicia-ka.github.io/iiif-test/annotations/G30495-02/anno_p49_no257.json",
      "@type": "oa:Annotation",
      "motivation": "oa:commenting",
      "resource": {
        "@type": "cnt:ContentAsText",
        "format": "text/plain",
        "chars": "fulhu,",
        "label": "name"
      },
      "on": "https://iiif.dl.itc.u-tokyo.ac.jp/repo/iiif/35f86a28-6c28-434b-a9fb-9182b8dbf0fa/canvas/p49#xywh=2016,1620,123,406",
      "metadata": [
        {
          "label": "type",
          "value": "name"
        },
        {
          "label": "sourceVolume",
          "value": "G30495-02"
        },
        {
          "label": "volume",
          "value": "巻一"
        },
        {
          "label": "sourceRow",
          "value": "257"
        }
      ],
      "stylesheet": {
        "@type": "oa:CssStyle",
        "chars": ".anno-257 { background-color: #54B5E2; opacity: 0.34; }"
      }
    },
    {
      "@id": "https://alicia-ka.github.io/iiif-test/annotations/G30495-02/anno_p49_no258.json",
      "@type": "oa:Annotation",
      "motivation": "oa:commenting",
      "resource": {
        "@type": "cnt:ContentAsText",
        "format": "text/plain",
        "chars": "tohiyan,",
        "label": "name"
      },
      "on": "https://iiif.dl.itc.u-tokyo.ac.jp/repo/iiif/35f86a28-6c28-434b-a9fb-9182b8dbf0fa/canvas/p49#xywh=3920,1606,137,392",
      "metadata": [
        {
          "label": "type",
          "value": "name"
        },
        {
          "label": "sourceVolume",
          "value": "G30495-02"
        },
        {
          "label": "volume",
          "value": "巻一"
        },
        {
          "label": "sourceRow",
          "value": "258"
        }
      ],
      "stylesheet": {
        "@type": "oa:CssStyle",
        "chars": ".anno-258 { background-color: #54B5E2; opacity: 0.34; }"
      }
    },
    {
      "@id": "https://alicia-ka.github.io/iiif-test/annotations/G30495-02/anno_p49_no259.json",
      "@type": "oa:Annotation",
      "motivation": "oa:commenting",
      "resource": {
        "@type": "cnt:ContentAsText",
        "format": "text/plain",
        "chars": "hadufun,",
        "label": "name"
      },
      "on": "https://iiif.dl.itc.u-tokyo.ac.jp/repo/iiif/35f86a28-6c28-434b-a9fb-9182b8dbf0fa/canvas/p49#xywh=5432,1599,154,409",
      "metadata": [
        {
          "label": "type",
          "value": "name"
        },
        {
          "label": "sourceVolume",
          "value": "G30495-02"
        },
        {
          "label": "volume",
          "value": "巻一"
        },
        {
          "label": "sourceRow",
          "value": "259"
        }
      ],
      "stylesheet": {
        "@type": "oa:CssStyle",
        "chars": ".anno-259 { background-color: #54B5E2; opacity: 0.34; }"
      }
    }
  ]
}